qfrm/American.py
qfrm/Asian.py
qfrm/Barrier.py
qfrm/Basket.py
qfrm/Bermudan.py
qfrm/Binary.py
qfrm/Boston.py
qfrm/Chooser.py
qfrm/Compound.py
qfrm/ContingentPremium.py
qfrm/European.py
qfrm/Exchange.py
qfrm/ForwardStart.py
qfrm/Gap.py
qfrm/Ladder.py
qfrm/Lookback.py
qfrm/LowExercisePrice.py
qfrm/OptionValuation.py
qfrm/PerpetualAmerican.py
qfrm/Quanto.py
qfrm/Rainbow.py
qfrm/Shout.py
qfrm/Spread.py
qfrm/Util.py
qfrm/VarianceSwap.py
qfrm/__init__.py
qfrm/_qfrm_.py
qfrm/conf.py
qfrm/qfrm.py
qfrm-0.2.0.27.dist-info/DESCRIPTION.rst
qfrm-0.2.0.27.dist-info/METADATA
qfrm-0.2.0.27.dist-info/RECORD
qfrm-0.2.0.27.dist-info/WHEEL
qfrm-0.2.0.27.dist-info/metadata.json
qfrm-0.2.0.27.dist-info/top_level.txt
